sng4onnx/__init__.py
sng4onnx/__main__.py
sng4onnx/onnx_opname_generator.py
sng4onnx-1.0.5.dist-info/licenses/LICENSE
sng4onnx-1.0.5.dist-info/METADATA
sng4onnx-1.0.5.dist-info/WHEEL
sng4onnx-1.0.5.dist-info/entry_points.txt
sng4onnx-1.0.5.dist-info/top_level.txt
sng4onnx-1.0.5.dist-info/RECORD
