Metadata-Version: 2.4
Name: sng4onnx
Version: 1.0.5
Summary: A simple tool that automatically generates and assigns an OP name to each OP in an old format ONNX file.
Home-page: https://github.com/PINTO0309/sng4onnx
Author: Katsuya Hyodo
Author-email: rmsdh122@yahoo.co.jp
License: MIT License
Platform: linux
Platform: unix
Requires-Python: >=3.6
License-File: LICENSE
Dynamic: author
Dynamic: author-email
Dynamic: description
Dynamic: description-content-type
Dynamic: home-page
Dynamic: license
Dynamic: license-file
Dynamic: platform
Dynamic: requires-python
Dynamic: summary
